Metadata-Version: 2.4
Name: adafruit-circuitpython-ssd1675
Version: 2.0.3
Summary: CircuitPython `displayio` drivers for SSD1675-based ePaper displays
Author-email: Adafruit Industries <circuitpython@adafruit.com>
License: MIT
Project-URL: Homepage, https://github.com/adafruit/Adafruit_CircuitPython_SSD1675
Keywords: adafruit,blinka,circuitpython,micropython,ssd1675,displayio,epd,epaper
Classifier: Intended Audience :: Developers
Classifier: Topic :: Software Development :: Libraries
Classifier: Topic :: Software Development :: Embedded Systems
Classifier: Topic :: System :: Hardware
Classifier: License :: OSI Approved :: MIT License
Classifier: Programming Language :: Python :: 3
License-File: LICENSE
Requires-Dist: Adafruit-Blinka
Provides-Extra: optional
Dynamic: license-file
